{
  "sources": [
    {
      "elements": [
        "Structure",
        "Environmental Controls"
      ],
      "description": "",
      "elementId": "2-2",
      "id": 0
    },
    {
      "elements": [
        "Actor",
        "Group"
      ],
      "description": "Bei den Angreifern handelt es sich um eine bekannte Hackergruppe",
      "elementId": "1-2",
      "id": 8
    }
  ],
  "events": [
    {
      "elements": [
        "Technical"
      ],
      "description": "",
      "elementId": "2",
      "id": 1,
      "triggeredBy": 4
    },
    {
      "elements": [
        "Technical",
        "Failures/Malfunctions"
      ],
      "description": "",
      "elementId": "2-2",
      "id": 4,
      "triggeredBy": 0
    },
    {
      "elements": [
        "Attack",
        "Physical attacks",
        "Unauthorised entry to premises"
      ],
      "description": "",
      "elementId": "1-2-3",
      "id": 5
    }
  ],
  "entities": [
    {
      "elements": [
        "Individuals"
      ],
      "description": "Menschen wurden verletzt",
      "elementId": "3",
      "id": 2
    },
    {
      "elements": [
        "Operations"
      ],
      "description": "Prozesse wurden gestört",
      "elementId": "1",
      "id": 6
    }
  ],
  "impacts": [
    {
      "elements": [
        "Moderate"
      ],
      "description": "",
      "elementId": "3",
      "id": 3
    }
  ],
  "idCount": 9
}